[{"id": "aae6d92e-5f28-43ee-b0dc-522e80e99f76", "name": "Peyton Manning", "jersey": "18", "reference": "00-0010346", "position": "QB", "games_played": 1, "games_started": 1, "rushing": {"avg_yards": -2.0, "attempts": 1, "touchdowns": 0, "yards": -2, "longest": -2, "longest_touchdown": 0, "redzone_attempts": 0}, "passing": {"attempts": 32, "completions": 17, "cmp_pct": 53.125, "yards": 194, "avg_yards": 6.063, "sacks": 0, "sack_yards": 0, "touchdowns": 1, "longest": 30, "interceptions": 0, "rating": 82.0, "longest_touchdown": 17, "air_yards": 0, "redzone_attempts": 4, "gross_yards": 194, "net_yards": 194}, "conversions": {"pass_attempts": 1, "pass_successes": 1, "rush_attempts": 0, "rush_successes": 0, "receive_attempts": 0, "receive_successes": 0, "defense_attempts": 0, "defense_successes": 0}, "team": "Colts", "year": 2000, "type": "PST"}, {"id": "ee6e9809-843e-42c8-934e-6f10ab38ad80", "name": "Billy Joe Hobert", "jersey": "14", "reference": "00-0007530", "position": "QB", "games_played": 0, "games_started": 0, "team": "Colts", "year": 2000, "type": "PST"}, {"id": "53ad15e7-d01c-4af0-8136-55b304dc3d61", "name": "Todd Bouman", "jersey": "4", "reference": "00-0001545", "position": "QB", "games_played": 0, "games_started": 0, "team": "Vikings", "year": 2000, "type": "PST"}, {"id": "df1a3fa7-4ffc-4121-83ae-5641e21bec0b", "name": "Daunte Culpepper", "jersey": "11", "reference": "00-0003739", "position": "QB", "games_played": 2, "games_started": 2, "rushing": {"avg_yards": 10.167, "attempts": 6, "touchdowns": 0, "yards": 61, "longest": 30, "longest_touchdown": 0, "redzone_attempts": 1, "tlost": 0, "tlost_yards": 0, "broken_tackles": 0, "kneel_downs": 0, "scrambles": 0, "yards_after_contact": 0}, "passing": {"attempts": 59, "completions": 30, "cmp_pct": 50.847, "yards": 380, "avg_yards": 6.441, "sacks": 4, "sack_yards": 18, "touchdowns": 3, "longest": 68, "interceptions": 3, "rating": 67.1, "longest_touchdown": 68, "air_yards": 0, "redzone_attempts": 4, "gross_yards": 380, "throw_aways": 0, "poor_throws": 0, "defended_passes": 0, "dropped_passes": 0, "spikes": 0, "blitzes": 0, "hurries": 0, "knockdowns": 0, "pocket_time": 0.0, "avg_pocket_time": 0.0}, "fumbles": {"fumbles": 2, "lost_fumbles": 1, "own_rec": 0, "own_rec_yards": 0, "opp_rec": 0, "opp_rec_yards": 0, "out_of_bounds": 1, "forced_fumbles": 0, "own_rec_tds": 0, "opp_rec_tds": 0, "ez_rec_tds": 0}, "team": "Vikings", "year": 2000, "type": "PST"}, {"id": "feffd833-b130-4f8a-af47-53b15cb7db5c", "name": "Bubby Brister", "jersey": "6", "reference": "00-0001785", "position": "QB", "games_played": 1, "games_started": 0, "team": "Vikings", "year": 2000, "type": "PST"}, {"id": "af18b3cd-9ce8-4dd7-bc18-efe2467992aa", "name": "Neil O'Donnell", "jersey": "14", "reference": "00-0012261", "position": "QB", "games_played": 1, "games_started": 0, "passing": {"attempts": 1, "completions": 1, "cmp_pct": 100.0, "yards": 19, "avg_yards": 19.0, "sacks": 0, "sack_yards": 0, "touchdowns": 0, "longest": 19, "interceptions": 0, "rating": 118.8, "longest_touchdown": 0, "air_yards": 0, "redzone_attempts": 0, "gross_yards": 19, "net_yards": 19}, "team": "Titans", "year": 2000, "type": "PST"}, {"id": "9cd9d06c-5650-41da-9918-88c4492378d5", "name": "Jay Fiedler", "jersey": "9", "reference": "00-0005180", "position": "QB", "games_played": 2, "games_started": 2, "rushing": {"avg_yards": 5.5, "attempts": 10, "touchdowns": 0, "yards": 55, "longest": 11, "longest_touchdown": 0, "redzone_attempts": 1}, "passing": {"attempts": 71, "completions": 37, "cmp_pct": 52.113, "yards": 361, "avg_yards": 5.085, "sacks": 4, "sack_yards": 21, "touchdowns": 1, "longest": 33, "interceptions": 6, "rating": 36.2, "longest_touchdown": 9, "air_yards": 0, "redzone_attempts": 4, "gross_yards": 361, "net_yards": 340}, "team": "Dolphins", "year": 2000, "type": "PST"}, {"id": "d5c4236d-8b87-4e67-962e-c62bb0d3e5d2", "name": "Billy Joe Tolliver", "jersey": "11", "reference": "00-0016534", "position": "QB", "games_played": 0, "games_started": 0, "team": "Saints", "year": 2000, "type": "PST"}, {"id": "2708a50f-9273-48f2-bcb3-4645119c3910", "name": "Kerry Collins", "jersey": "5", "reference": "00-0003292", "position": "QB", "games_played": 3, "games_started": 3, "rushing": {"avg_yards": 2.636, "attempts": 11, "touchdowns": 0, "yards": 29, "longest": 9, "longest_touchdown": 0, "redzone_attempts": 0, "tlost": 0, "tlost_yards": 0, "broken_tackles": 0, "kneel_downs": 0, "scrambles": 0, "yards_after_contact": 0}, "passing": {"attempts": 97, "completions": 55, "cmp_pct": 56.701, "yards": 618, "avg_yards": 6.371, "sacks": 5, "sack_yards": 26, "touchdowns": 5, "longest": 46, "interceptions": 6, "rating": 67.3, "longest_touchdown": 46, "air_yards": 0, "redzone_attempts": 14, "gross_yards": 618, "throw_aways": 0, "poor_throws": 0, "defended_passes": 0, "dropped_passes": 0, "spikes": 0, "blitzes": 0, "hurries": 0, "knockdowns": 0, "pocket_time": 0.0, "avg_pocket_time": 0.0}, "fumbles": {"fumbles": 1, "lost_fumbles": 0, "own_rec": 0, "own_rec_yards": 0, "opp_rec": 0, "opp_rec_yards": 0, "out_of_bounds": 0, "forced_fumbles": 0, "own_rec_tds": 0, "opp_rec_tds": 0, "ez_rec_tds": 0}, "team": "Giants", "year": 2000, "type": "PST"}, {"id": "57ad6a99-d377-42a5-b576-068215f5dadf", "name": "Eric Zeier", "jersey": "15", "reference": "00-0018483", "position": "QB", "games_played": 0, "games_started": 0, "team": "Buccaneers", "year": 2000, "type": "PST"}, {"id": "0d4e17a5-a212-48fd-b807-b280f8cbdb62", "name": "Kurt Warner", "jersey": "13", "reference": "00-0017200", "position": "QB", "games_played": 1, "games_started": 1, "rushing": {"avg_yards": 5.0, "attempts": 1, "touchdowns": 1, "yards": 5, "longest": 5, "longest_touchdown": 5, "redzone_attempts": 1, "tlost": 0, "tlost_yards": 0, "broken_tackles": 0, "kneel_downs": 0, "scrambles": 0, "yards_after_contact": 0}, "passing": {"attempts": 40, "completions": 24, "cmp_pct": 60.0, "yards": 365, "avg_yards": 9.125, "sacks": 2, "sack_yards": 15, "touchdowns": 3, "longest": 38, "interceptions": 3, "rating": 83.9, "longest_touchdown": 25, "air_yards": 0, "redzone_attempts": 4, "gross_yards": 365, "throw_aways": 0, "poor_throws": 0, "defended_passes": 0, "dropped_passes": 0, "spikes": 0, "blitzes": 0, "hurries": 0, "knockdowns": 0, "pocket_time": 0.0, "avg_pocket_time": 0.0}, "fumbles": {"fumbles": 1, "lost_fumbles": 1, "own_rec": 0, "own_rec_yards": 0, "opp_rec": 0, "opp_rec_yards": 0, "out_of_bounds": 0, "forced_fumbles": 0, "own_rec_tds": 0, "opp_rec_tds": 0, "ez_rec_tds": 0}, "conversions": {"pass_attempts": 1, "pass_successes": 1, "rush_attempts": 0, "rush_successes": 0, "receive_attempts": 0, "receive_successes": 0, "defense_attempts": 0, "defense_successes": 0}, "team": "Rams", "year": 2000, "type": "PST"}, {"id": "42c40c79-04ed-4342-90c4-fa05579bf527", "name": "Trent Green", "jersey": "12", "reference": "00-0006355", "position": "QB", "games_played": 0, "games_started": 0, "team": "Rams", "year": 2000, "type": "PST"}, {"id": "67b03266-ba53-42de-b03f-17f596dda135", "name": "Koy Detmer", "jersey": "10", "reference": "00-0004229", "position": "QB", "games_played": 2, "games_started": 0, "team": "Eagles", "year": 2000, "type": "PST"}, {"id": "f53999b7-0867-4c33-a093-58b0122ee794", "name": "Donovan McNabb", "jersey": "5", "reference": "00-0011022", "position": "QB", "games_played": 2, "games_started": 2, "rushing": {"avg_yards": 3.769, "attempts": 13, "touchdowns": 1, "yards": 49, "longest": 11, "longest_touchdown": 5, "redzone_attempts": 2, "tlost": 0, "tlost_yards": 0, "broken_tackles": 0, "kneel_downs": 0, "scrambles": 0, "yards_after_contact": 0}, "passing": {"attempts": 74, "completions": 44, "cmp_pct": 59.459, "yards": 342, "avg_yards": 4.622, "sacks": 8, "sack_yards": 51, "touchdowns": 3, "longest": 25, "interceptions": 2, "rating": 73.1, "longest_touchdown": 10, "air_yards": 0, "redzone_attempts": 13, "gross_yards": 342, "throw_aways": 0, "poor_throws": 0, "defended_passes": 0, "dropped_passes": 0, "spikes": 0, "blitzes": 0, "hurries": 0, "knockdowns": 0, "pocket_time": 0.0, "avg_pocket_time": 0.0}, "fumbles": {"fumbles": 2, "lost_fumbles": 1, "own_rec": 1, "own_rec_yards": -1, "opp_rec": 0, "opp_rec_yards": 0, "out_of_bounds": 0, "forced_fumbles": 0, "own_rec_tds": 0, "opp_rec_tds": 0, "ez_rec_tds": 0}, "defense": {"tackles": 0, "assists": 0, "combined": 0, "sacks": 0.0, "sack_yards": 0.0, "interceptions": 0, "passes_defended": 0, "forced_fumbles": 0, "fumble_recoveries": 0, "qb_hits": 0, "tloss": 0.0, "tloss_yards": 0.0, "safeties": 0, "sp_tackles": 0, "sp_assists": 0, "sp_forced_fumbles": 0, "sp_fumble_recoveries": 0, "sp_blocks": 0, "misc_tackles": 0, "misc_assists": 0, "misc_forced_fumbles": 0, "misc_fumble_recoveries": 1, "def_targets": 0, "def_comps": 0, "blitzes": 0, "hurries": 0, "knockdowns": 0, "missed_tackles": 0}, "team": "Eagles", "year": 2000, "type": "PST"}, {"id": "958143ee-8e6a-45e1-811b-7ac5959e7441", "name": "Trent Dilfer", "jersey": "12", "reference": "00-0004293", "position": "QB", "games_played": 4, "games_started": 4, "rushing": {"avg_yards": 0.538, "attempts": 13, "touchdowns": 0, "yards": 7, "longest": 6, "longest_touchdown": 0, "redzone_attempts": 1}, "passing": {"attempts": 73, "completions": 35, "cmp_pct": 47.945, "yards": 590, "avg_yards": 8.082, "sacks": 10, "sack_yards": 82, "touchdowns": 3, "longest": 96, "interceptions": 1, "rating": 83.7, "longest_touchdown": 96, "air_yards": 0, "redzone_attempts": 3, "gross_yards": 590, "net_yards": 508}, "fumbles": {"fumbles": 3, "lost_fumbles": 0, "own_rec": 1, "own_rec_yards": -1, "opp_rec": 0, "opp_rec_yards": 0, "out_of_bounds": 0, "forced_fumbles": 0, "own_rec_tds": 0, "opp_rec_tds": 0, "ez_rec_tds": 0}, "defense": {"tackles": 0, "assists": 0, "combined": 0, "sacks": 0.0, "sack_yards": 0.0, "interceptions": 0, "passes_defended": 0, "forced_fumbles": 0, "fumble_recoveries": 0, "qb_hits": 0, "tloss": 0.0, "tloss_yards": 0.0, "safeties": 0, "sp_tackles": 0, "sp_assists": 0, "sp_forced_fumbles": 0, "sp_fumble_recoveries": 0, "sp_blocks": 0, "misc_tackles": 0, "misc_assists": 0, "misc_forced_fumbles": 0, "misc_fumble_recoveries": 1}, "team": "Ravens", "year": 2000, "type": "PST"}, {"id": "eded139b-8692-4d78-8ebe-c2b85d561ceb", "name": "Tony Banks", "jersey": "12", "reference": "00-0000722", "position": "QB", "games_played": 3, "games_started": 0, "rushing": {"avg_yards": -1.0, "attempts": 1, "touchdowns": 0, "yards": -1, "longest": -1, "longest_touchdown": 0, "redzone_attempts": 0}, "passing": {"attempts": 3, "completions": 0, "cmp_pct": 0.0, "yards": 0, "avg_yards": 0.0, "sacks": 0, "sack_yards": 0, "touchdowns": 0, "longest": 0, "interceptions": 0, "rating": 39.6, "longest_touchdown": 0, "air_yards": 0, "redzone_attempts": 0, "gross_yards": 0, "net_yards": 0}, "team": "Ravens", "year": 2000, "type": "PST"}, {"id": "36dadb30-0d3c-4ee7-bffb-a107c5d645af", "name": "Jarious Jackson", "jersey": "17", "reference": "00-0019682", "position": "QB", "games_played": 1, "games_started": 0, "passing": {"attempts": 10, "completions": 5, "cmp_pct": 50.0, "yards": 54, "avg_yards": 5.4, "sacks": 1, "sack_yards": 9, "touchdowns": 0, "longest": 19, "interceptions": 0, "rating": 66.3, "longest_touchdown": 0, "air_yards": 0, "redzone_attempts": 0, "gross_yards": 54, "net_yards": 45}, "team": "Broncos", "year": 2000, "type": "PST"}, {"id": "44dedcee-15ae-4e82-81f3-c9186b82673c", "name": "Gus Frerotte", "jersey": "12", "reference": "00-0005589", "position": "QB", "games_played": 1, "games_started": 1, "rushing": {"avg_yards": -1.0, "attempts": 1, "touchdowns": 0, "yards": -1, "longest": -1, "longest_touchdown": 0, "redzone_attempts": 0}, "passing": {"attempts": 28, "completions": 13, "cmp_pct": 46.429, "yards": 124, "avg_yards": 4.429, "sacks": 4, "sack_yards": 34, "touchdowns": 0, "longest": 24, "interceptions": 1, "rating": 44.3, "longest_touchdown": 0, "air_yards": 0, "redzone_attempts": 0, "gross_yards": 124, "net_yards": 90}, "team": "Broncos", "year": 2000, "type": "PST"}, {"id": "63fb201b-203a-4876-a4a5-e395ddde555b", "name": "Terrell Buckley", "jersey": "22", "reference": "00-0002185", "position": "QB", "games_played": 1, "games_started": 1, "punt_returns": {"returns": 0, "yards": 0, "avg_yards": 0.0, "touchdowns": 0, "longest": 0, "faircatches": 1, "longest_touchdown": 0}, "team": "Broncos", "year": 2000, "type": "PST"}]